Metadata-Version: 2.1
Name: tscode
Version: 0.4.16
Summary: Computational chemistry general purpose transition state builder and ensemble optimizer
Home-page: https://www.github.com/ntampellini/tscode
Author: Nicolò Tampellini
Author-email: nicolo.tampellini@yale.edu
Keywords: computational chemistry,ASE,transition state,xtb
Classifier: Programming Language :: Python :: 3
Classifier: Programming Language :: Python :: 3.8
Classifier: License :: OSI Approved :: GNU General Public License v3 (GPLv3)
Classifier: Operating System :: OS Independent
Requires-Python: >=3.8
License-File: LICENSE
Requires-Dist: numpy
Requires-Dist: scipy
Requires-Dist: numba-scipy ==0.3.0
Requires-Dist: cclib ==1.7
Requires-Dist: periodictable ==1.6.0
Requires-Dist: matplotlib ==3.4.2
Requires-Dist: networkx ==2.5.1
Requires-Dist: rmsd ==1.4
Requires-Dist: ase ==3.21.1
Requires-Dist: sella ==2.3.2
Requires-Dist: scikit-learn ==1.0.1
Requires-Dist: numba ==0.54.1
Requires-Dist: prettytable ==3.3.0
Requires-Dist: typing-extensions ==4.8.0
Requires-Dist: llvmlite
Requires-Dist: importlib-metadata ==7.0.1
